play_football_match_highlights/__init__.py
play_football_match_highlights/main.py
play_football_match_highlights-0.1.0.dist-info/LICENSE
play_football_match_highlights-0.1.0.dist-info/METADATA
play_football_match_highlights-0.1.0.dist-info/WHEEL
play_football_match_highlights-0.1.0.dist-info/entry_points.txt
play_football_match_highlights-0.1.0.dist-info/RECORD
