Metadata-Version: 2.1
Name: play_football_match_highlights
Version: 0.1.0
Summary: Play football match highlights without ads.
Home-page: https://github.com/zhiwei2017/play-football-match-highlights
License: MIT
Author: Zhiwei Zhang
Author-email: zhiwei2017@gmail.com
Requires-Python: >=3.10,<4.0
Classifier: License :: OSI Approved :: MIT License
Classifier: Programming Language :: Python :: 3
Classifier: Programming Language :: Python :: 3.10
Classifier: Programming Language :: Python :: 3.11
Classifier: Programming Language :: Python :: 3.12
Classifier: Programming Language :: Python :: 3.13
Requires-Dist: click (>=8.1.7,<9.0.0)
Requires-Dist: lxml-html-clean (>=0.3.1,<0.4.0)
Requires-Dist: requests-html (>=0.10.0,<0.11.0)
Project-URL: Documentation, https://github.com/zhiwei2017/play-football-match-highlights
Project-URL: Repository, https://github.com/zhiwei2017/play-football-match-highlights
